Workbook

Sheet Rate Card
A1: Name | B1: Jira Name | C1: Monthly Salary
A2: Alice | C2: 80000
A3: Bob | C3: 60000
A4: Charlie | C4: 100000

Sheet Holidays
A1: Date | B1: Description
A2: 2026-01-26 | B2: Republic Day
A3: 2026-03-01 | B3: Sample Holiday

Sheet Resource List
A1: Name | B1: Jira Name | C1: Date of Joining | D1: Date of Separation | E1: Period Start | F1: Period End | G1: Required Hours (Formula)
A2: Alice | C2: 2024-01-01 | E2: 2026-01-01 | F2: 2026-03-31 | G2: =NETWORKDAYS.INTL(E2,F2,1, Holidays!A2:A100)*8 -> 504
A3: Bob | C3: 2024-01-01 | E3: 2026-01-01 | F3: 2026-03-31 | G3: =NETWORKDAYS.INTL(E3,F3,1, Holidays!A2:A100)*8 -> 504
A4: Charlie | C4: 2024-01-01 | E4: 2026-01-01 | F4: 2026-03-31 | G4: =NETWORKDAYS.INTL(E4,F4,1, Holidays!A2:A100)*8 -> 504

Sheet Jira Dump
A1: Author | B1: Project | C1: Issue | D1: Epic | E1: Original Estimate | F1: Project Category | G1: Started Day | H1: Time Spent (hrs) | I1: Project Key (formula) | J1: Total Jira Hours (per author) | K1: Required Hours (lookup) | L1: Remark (To cap?) | M1: Capped Hours (calc) | N1: Monthly Salary (lookup) | O1: Hourly Rate | P1: Row Cost
A2: Alice | C2: SEYL-101 | D2: FY26 Q4 | F2: Implementation | G2: 2026-01-05 | H2: 90 | I2: =LEFT(C2,FIND("-",C2)-1) -> SEYL | J2: =SUMIFS(H:H, A:A, A2) -> 190 | K2: =VLOOKUP(A2, 'Resource List'!A:G, 7, FALSE) -> 504 | L2: =IF(J2>K2, "To cap", "") | M2: =IF(L2="To cap", (H2/J2)*K2, H2) -> 90 | N2: =VLOOKUP(A2, 'Rate Card'!A:C, 2, FALSE) -> 0 | O2: =IF(N2="", "", N2/22/8) -> 0 | P2: =M2 * O2 -> 0
A3: Alice | C3: SEYL-102 | D3: FY26 Q4 | F3: Implementation | G3: 2026-02-10 | H3: 100 | I3: =LEFT(C3,FIND("-",C3)-1) -> SEYL | J3: =SUMIFS(H:H, A:A, A3) -> 190 | K3: =VLOOKUP(A3, 'Resource List'!A:G, 7, FALSE) -> 504 | L3: =IF(J3>K3, "To cap", "") | M3: =IF(L3="To cap", (H3/J3)*K3, H3) -> 100 | N3: =VLOOKUP(A3, 'Rate Card'!A:C, 2, FALSE) -> 0 | O3: =IF(N3="", "", N3/22/8) -> 0 | P3: =M3 * O3 -> 0
A4: Bob | C4: ABCD-201 | D4: FY26 Q4 | F4: Consulting | G4: 2026-01-15 | H4: 120 | I4: =LEFT(C4,FIND("-",C4)-1) -> ABCD | J4: =SUMIFS(H:H, A:A, A4) -> 120 | K4: =VLOOKUP(A4, 'Resource List'!A:G, 7, FALSE) -> 504 | L4: =IF(J4>K4, "To cap", "") | M4: =IF(L4="To cap", (H4/J4)*K4, H4) -> 120 | N4: =VLOOKUP(A4, 'Rate Card'!A:C, 2, FALSE) -> 0 | O4: =IF(N4="", "", N4/22/8) -> 0 | P4: =M4 * O4 -> 0
A5: Charlie | C5: SEYL-103 | D5: FY26 Q4 | F5: Implementation | G5: 2026-03-05 | H5: 150 | I5: =LEFT(C5,FIND("-",C5)-1) -> SEYL | J5: =SUMIFS(H:H, A:A, A5) -> 150 | K5: =VLOOKUP(A5, 'Resource List'!A:G, 7, FALSE) -> 504 | L5: =IF(J5>K5, "To cap", "") | M5: =IF(L5="To cap", (H5/J5)*K5, H5) -> 150 | N5: =VLOOKUP(A5, 'Rate Card'!A:C, 2, FALSE) -> 0 | O5: =IF(N5="", "", N5/22/8) -> 0 | P5: =M5 * O5 -> 0

Sheet Jira 2.0
A1: SR Number | B1: Customer Name | C1: Product | D1: Category | E1: Category Code | F1: Client Code | G1: Sequence | H1: Project Key (formula) | I1: PO Amount | J1: Revenue FY25 | K1: Revenue FY26 | L1: Total Signed HR Cost
A2: 1 | B2: Seylan Bank | C2: Lending | D2: Implementation | E2: IMP | F2: SEYL | G2: 1 | H2: =F2 & "-" & E2 & "-" & TEXT(G2,"00") -> SEYL-IMP-01 | I2: 500000 | J2: 200000 | K2: 100000 | L2: 300000
A3: 2 | B3: Alpha Corp | C3: Payments | D3: Consulting | E3: CON | F3: ABCD | G3: 1 | H3: =F3 & "-" & E3 & "-" & TEXT(G3,"00") -> ABCD-CON-01 | I3: 300000 | J3: 100000 | K3: 50000 | L3: 150000

Sheet Overhead Pool
A1: Quarter | B1: HR Overhead Total | C1: OPE Total | D1: Infra Total | E1: Commission Total
A2: FY26 Q4 | B2: 50000 | C2: 25000 | D2: 15000 | E2: 10000

Sheet Final Report
A1: Project | B1: Product | C1: Category | D1: Project Key | E1: Project Status | F1: PO Amount | G1: Revenue FY25 | H1: Revenue FY26 | I1: Cumulative Revenue | J1: Budget To Go | K1: Total Signed HR Cost | L1: Cost Till Last Quarter | M1: Opening Remaining Signed HR Cost | N1: Cost Incurred Current Quarter | O1: Total Direct Cost Till Date | P1: Closing Remaining Signed HR Cost | Q1: Allocated HR Overhead | R1: OPE Cost | S1: Infra Cost | T1: Partnership Commission | U1: Total Fully Loaded Cost | V1: Gross Profit | W1: Gross Margin %
A2: Seylan Implementation | B2: Lending | C2: Implementation | D2: SEYL-IMP-01 | E2: Active | F2: 500000 | G2: 200000 | H2: 100000 | I2: =G2+H2 -> 300000 | J2: =F2-I2 -> 200000 | K2: 300000 | L2: 150000 | M2: =K2-L2 -> 150000 | N2: =SUMIFS('Jira Dump'!P:P, 'Jira Dump'!I:I, D2, 'Jira Dump'!D:D, "FY26 Q4") -> 0 | O2: =L2+N2 -> 150000 | P2: =M2-N2 -> 150000 | Q2: =O2 / SUM($O$2:$O$3) * 'Overhead Pool'!B2 -> 34090.909 | R2: =O2 / SUM($O$2:$O$3) * 'Overhead Pool'!C2 -> 17045.455 | S2: =O2 / SUM($O$2:$O$3) * 'Overhead Pool'!D2 -> 10227.273 | T2: =O2 / SUM($O$2:$O$3) * 'Overhead Pool'!E2 -> 6818.1818 | U2: =O2 + Q2 + R2 + S2 + T2 -> 218181.82 | V2: =I2 - U2 -> 81818.182 | W2: =IF(I2=0,0,V2/I2) -> 0.27272727
A3: Alpha Consulting | B3: Payments | C3: Consulting | D3: ABCD-CON-01 | E3: Active | F3: 300000 | G3: 100000 | H3: 50000 | I3: =G3+H3 -> 150000 | J3: =F3-I3 -> 150000 | K3: 150000 | L3: 70000 | M3: =K3-L3 -> 80000 | N3: =SUMIFS('Jira Dump'!P:P, 'Jira Dump'!I:I, D3, 'Jira Dump'!D:D, "FY26 Q4") -> 0 | O3: =L3+N3 -> 70000 | P3: =M3-N3 -> 80000 | Q3: =O3 / SUM($O$2:$O$3) * 'Overhead Pool'!B2 -> 15909.091 | R3: =O3 / SUM($O$2:$O$3) * 'Overhead Pool'!C2 -> 7954.5455 | S3: =O3 / SUM($O$2:$O$3) * 'Overhead Pool'!D2 -> 4772.7273 | T3: =O3 / SUM($O$2:$O$3) * 'Overhead Pool'!E2 -> 3181.8182 | U3: =O3 + Q3 + R3 + S3 + T3 -> 101818.18 | V3: =I3 - U3 -> 48181.818 | W3: =IF(I3=0,0,V3/I3) -> 0.32121212
